{
  "pubdate": "2007-6", 
  "tags": [], 
  "price": "21.80元", 
  "pages": "68", 
  "publisher": "贵州人民出版社", 
  "isbn13": "9787221077035", 
  "author": "理查德·斯凯瑞", 
  "title": "轱辘轱辘转", 
  "author_intro": "", 
  "summary": "《斯凯瑞金色童书(第1辑):轱辘轱辘转》精心设计了多条并行的线索，毛美丽警官追捕司机皮皮狗，全能鼠妹解救陷在困境中的车辆，到处乱窜的金虫子一直隐藏在画面中。书中的丰富细节可以让孩子反复阅读，在游戏中培养他们的观察力和想像力。《轱辘轱辘转》通过小猪一家在混乱中冒险的旅程，介绍了四百余种车型。这些千奇百怪的车辆，一定会让小读者大开眼界。作为一本启蒙读物，《斯凯瑞金色童书第1辑:轱辘轱辘转》汇集了航空、航海、铁路、公路等各种交通工具和工程车辆，孩子在认知这些名称的同时，也熟悉了它们的用途。其中有一些并不是生活中真正的车辆，而是作者有趣的想象，比如牙刷车、南瓜车、香蕉车、面包圈车。紧张激动、滑稽有趣的故事情节会给孩子带来无限的快乐体验。", 
  "image": "https://img3.doubanio.com/view/subject/m/public/s10273230.jpg"
}