{"pubdate": "2007-9-1", "tags": ["散文", "随笔", "思考", "人文", "文学", "季羡林", "散文随笔"], "price": "29.80元", "pages": "309", "publisher": "陕西师范大学出版社", "isbn13": "9787561338155", "author": " 季羡林", "title": "阅世心语", "author_intro": "季羡林，1911年出生于山东省清平县(现并入临清市)。曾在济南三合街小学、济南一中、山东大学就学。1930年考入清华大学西洋文学系。1935年考取清华大学与德国的交换研究生，赴德国入哥廷根大学学习梵文、巴利文和吐火罗文等。1941年获哲学博士学位。1946年回国，同年秋，经陈寅恪推荐，季羡林被聘为北京大学教授，创建东方语文系，任北京大学教授兼东方语言文学系主任。1956年当选为中国科学院哲学社会科学部委员。19 78年任北京大学副校长、中国社会科学院与北京大学合办的南亚研究所所长。1984年研究所分设，改任北京大学南亚东南亚研究所所长。他先后担任中国外国文学学会会长、中国南亚学会会长、中国民族古文字学会名誉会长、中国语言学会会长、中国外语教学研究会会长、中国高等教育学会副会长和中国敦煌吐鲁番学会会长等。著作已经汇编成《季羡林文集》，共有24卷，内容包...\\n(展开全部)", "summary": "季羡林先生是著名学者、国学大师、同时它还是著名的散文大家。他襟怀坦荡、学贯中西，读他的散文是一种享受，开怀释卷，典雅清丽的文字拂面而来，纯朴而不乏味，情浓而不矫作，庄重而不板滞，典雅而不雕琢。无论记人、状物或摹事，笔下流淌的是炙热的人文情怀，充满着趣味和韵味。本书收录了季羡林先生关于人生、治学、生活等方面的文章，从中可以窥见国学大师的生活态度，耄耋老人的人生感悟、对于人生意义与价值的追寻、缘分与命运、做人与处世、容忍、成功、知足、朋友、毁誉、压力、长寿之道、伦理道德等方面。是学术大家季羡林先生结合自己九十多年的生活体验，对于人生和世事的感悟的集大成之作。", "image": "https://img9.doubanio.com/view/subject/m/public/s8898955.jpg"}